generateNscore/__init__.py
generateNscore/_common.py
generateNscore/_generateEm.py
generateNscore/_generateMakeHTMLs.py
generateNscore/_scoreEm.py
generateNscore/makeChoices.py
generatenscore-1.0.8.dist-info/METADATA
generatenscore-1.0.8.dist-info/WHEEL
generatenscore-1.0.8.dist-info/licenses/LICENSE.txt
generatenscore-1.0.8.dist-info/RECORD
