Metadata-Version: 2.1
Name: generateNscore
Version: 1.0.8
Summary: A package to generate question sheets in HTML files and to score answers in text files
Project-URL: Homepage, https://github.com/generateNscore/generateNscore
Project-URL: Bug Tracker, https://github.com/generateNscore/generateNscore/issues
Author-email: Sukmock Lee <smlee@inha.ac.kr>
License-File: LICENSE.txt
Classifier: Development Status :: 3 - Alpha
Classifier: Intended Audience :: Education
Classifier: Intended Audience :: End Users/Desktop
Classifier: License :: OSI Approved :: MIT License
Classifier: Operating System :: OS Independent
Classifier: Programming Language :: Python :: 3
Classifier: Topic :: Education :: Testing
Requires-Python: >=3.7
